{"SPDXID":"SPDXRef-DOCUMENT","spdxVersion":"SPDX-2.3","creationInfo":{"created":"2023-11-09T23:51:49Z","creators":["Tool: GitHub.com-Dependency-Graph"]},"name":"com.github.Benjoyo/ForceDirectedPlacement","dataLicense":"CC0-1.0","documentDescribes":["SPDXRef-com.github.Benjoyo-ForceDirectedPlacement"],"documentNamespace":"https://github.com/Benjoyo/ForceDirectedPlacement/dependency_graph/sbom-e28e62276dc18454","packages":[{"SPDXID":"SPDXRef-com.github.Benjoyo-ForceDirectedPlacement","name":"com.github.Benjoyo/ForceDirectedPlacement","versionInfo":"","downloadLocation":"git+https://github.com/Benjoyo/ForceDirectedPlacement","licenseDeclared":"MIT","filesAnalyzed":false,"supplier":"NOASSERTION","externalRefs":[{"referenceCategory":"PACKAGE-MANAGER","referenceType":"purl","referenceLocator":"pkg:github/Benjoyo/ForceDirectedPlacement"}]},{"SPDXID":"SPDXRef-maven-com.scireum-parsii-1.5","name":"maven:com.scireum:parsii","versionInfo":"1.5","downloadLocation":"NOASSERTION","filesAnalyzed":false,"supplier":"NOASSERTION","externalRefs":[{"referenceCategory":"PACKAGE-MANAGER","referenceLocator":"pkg:maven/com.scireum/parsii@1.5","referenceType":"purl"}]},{"SPDXID":"SPDXRef-maven-javax.vecmath-vecmath-1.5.2","name":"maven:javax.vecmath:vecmath","versionInfo":"1.5.2","downloadLocation":"NOASSERTION","filesAnalyzed":false,"supplier":"NOASSERTION","externalRefs":[{"referenceCategory":"PACKAGE-MANAGER","referenceLocator":"pkg:maven/javax.vecmath/vecmath@1.5.2","referenceType":"purl"}]},{"SPDXID":"SPDXRef-maven-org.apache.commons-commons-lang3-3.4","name":"maven:org.apache.commons:commons-lang3","versionInfo":"3.4","downloadLocation":"NOASSERTION","filesAnalyzed":false,"licenseConcluded":"Apache-2.0","supplier":"NOASSERTION","externalRefs":[{"referenceCategory":"PACKAGE-MANAGER","referenceLocator":"pkg:maven/org.apache.commons/commons-lang3@3.4","referenceType":"purl"}]},{"SPDXID":"SPDXRef-maven-org.jfree-jfreechart-1.0.14","name":"maven:org.jfree:jfreechart","versionInfo":"1.0.14","downloadLocation":"NOASSERTION","filesAnalyzed":false,"licenseConcluded":"LGPL-3.0","supplier":"NOASSERTION","externalRefs":[{"referenceCategory":"PACKAGE-MANAGER","referenceLocator":"pkg:maven/org.jfree/jfreechart@1.0.14","referenceType":"purl"}]},{"SPDXID":"SPDXRef-maven-org.jgrapht-jgrapht-core-1.0.0","name":"maven:org.jgrapht:jgrapht-core","versionInfo":"1.0.0","downloadLocation":"NOASSERTION","filesAnalyzed":false,"supplier":"NOASSERTION","externalRefs":[{"referenceCategory":"PACKAGE-MANAGER","referenceLocator":"pkg:maven/org.jgrapht/jgrapht-core@1.0.0","referenceType":"purl"}]}],"relationships":[{"relationshipType":"DEPENDS_ON","spdxElementId":"SPDXRef-com.github.Benjoyo-ForceDirectedPlacement","relatedSpdxElement":"SPDXRef-maven-com.scireum-parsii-1.5"},{"relationshipType":"DEPENDS_ON","spdxElementId":"SPDXRef-com.github.Benjoyo-ForceDirectedPlacement","relatedSpdxElement":"SPDXRef-maven-javax.vecmath-vecmath-1.5.2"},{"relationshipType":"DEPENDS_ON","spdxElementId":"SPDXRef-com.github.Benjoyo-ForceDirectedPlacement","relatedSpdxElement":"SPDXRef-maven-org.apache.commons-commons-lang3-3.4"},{"relationshipType":"DEPENDS_ON","spdxElementId":"SPDXRef-com.github.Benjoyo-ForceDirectedPlacement","relatedSpdxElement":"SPDXRef-maven-org.jfree-jfreechart-1.0.14"},{"relationshipType":"DEPENDS_ON","spdxElementId":"SPDXRef-com.github.Benjoyo-ForceDirectedPlacement","relatedSpdxElement":"SPDXRef-maven-org.jgrapht-jgrapht-core-1.0.0"}]}